KevinKarabinasPytrends/__init__.py
KevinKarabinasPytrends/dailydata.py
KevinKarabinasPytrends/exceptions.py
KevinKarabinasPytrends/request.py
KevinKarabinasPytrends/test_trendReq.py
KevinKarabinasPytrends-0.1.dist-info/METADATA
KevinKarabinasPytrends-0.1.dist-info/WHEEL
KevinKarabinasPytrends-0.1.dist-info/top_level.txt
KevinKarabinasPytrends-0.1.dist-info/RECORD
