Metadata-Version: 2.1
Name: KevinKarabinasPytrends
Version: 0.1
Summary: Please Work
Home-page: UNKNOWN
Author: Kevin Karabinas
Author-email: kevink@example.com
License: MIT
Platform: UNKNOWN
Requires-Dist: requests
Requires-Dist: pandas
Requires-Dist: lxml
